{"OutputFileHashSum":"EB93E931CF2ECFEC0C34C8EA4ADC12F6206C7DD324173BCE9B73F45FB1893B75","Converted":true,"OutputModifyDate":"2023-04-28T07:08:34.2556426Z","Metadatas":[],"MetadataTypes":[{"CategoryName":"VuGen.Replay","MetadataTypeName":"HP.LR.Vugen.Iteration","Id":1},{"CategoryName":"VuGen.Replay","MetadataTypeName":"HP.LR.Vugen.NotifyTransaction","Id":2},{"CategoryName":"VuGen.Replay","MetadataTypeName":"HP.LR.Vugen.NotifySavingParameter","Id":3},{"CategoryName":"VuGen.Replay","MetadataTypeName":"HP.LR.Vugen.NotifyParameterSubstitution","Id":4},{"CategoryName":"VuGen.Replay","MetadataTypeName":"HP.LR.Vugen.NotifyAny","Id":5}]}